{
  "results": {
    "tool": {
      "name": "playwright"
    },
    "summary": {
      "tests": 1,
      "passed": 0,
      "failed": 1,
      "pending": 0,
      "skipped": 0,
      "other": 0,
      "start": 1727919644844,
      "stop": 1727919650662,
      "suites": 0
    },
    "tests": [
      {
        "name": "Buy Energy page",
        "status": "failed",
        "duration": 5127,
        "start": 1727919645,
        "stop": 1727919650,
        "message": "Error: Subheading should include correct time and day\n\n\u001b[31mTimed out 1000ms waiting for \u001b[39m\u001b[2mexpect(\u001b[22m\u001b[31mlocator\u001b[39m\u001b[2m).\u001b[22mtoHaveText\u001b[2m(\u001b[22m\u001b[32mexpected\u001b[39m\u001b[2m)\u001b[22m\n\nLocator: locator('h4').first()\nExpected pattern: \u001b[32m/^The time is 2:40 AM on Thursday and the trading window is open$/\u001b[39m\nReceived string:  \u001b[31m\"The time is 1:40 AM on Thursday and the trading window is open\"\u001b[39m\nCall log:\n  \u001b[2m- Subheading should include correct time and day with timeout 1000ms\u001b[22m\n\u001b[2m  - waiting for locator('h4').first()\u001b[22m\n\u001b[2m  -   locator resolved to <h4>The time is 1:40 AM on Thursday and the trading w…</h4>\u001b[22m\n\u001b[2m  -   unexpected value \"The time is 1:40 AM on Thursday and the trading window is open\"\u001b[22m\n\u001b[2m  -   locator resolved to <h4>The time is 1:40 AM on Thursday and the trading w…</h4>\u001b[22m\n\u001b[2m  -   unexpected value \"The time is 1:40 AM on Thursday and the trading window is open\"\u001b[22m\n\u001b[2m  -   locator resolved to <h4>The time is 1:40 AM on Thursday and the trading w…</h4>\u001b[22m\n\u001b[2m  -   unexpected value \"The time is 1:40 AM on Thursday and the trading window is open\"\u001b[22m\n\u001b[2m  -   locator resolved to <h4>The time is 1:40 AM on Thursday and the trading w…</h4>\u001b[22m\n\u001b[2m  -   unexpected value \"The time is 1:40 AM on Thursday and the trading window is open\"\u001b[22m\n\u001b[2m  -   locator resolved to <h4>The time is 1:40 AM on Thursday and the trading w…</h4>\u001b[22m\n\u001b[2m  -   unexpected value \"The time is 1:40 AM on Thursday and the trading window is open\"\u001b[22m\n",
        "trace": "Error: Subheading should include correct time and day\n\n\u001b[31mTimed out 1000ms waiting for \u001b[39m\u001b[2mexpect(\u001b[22m\u001b[31mlocator\u001b[39m\u001b[2m).\u001b[22mtoHaveText\u001b[2m(\u001b[22m\u001b[32mexpected\u001b[39m\u001b[2m)\u001b[22m\n\nLocator: locator('h4').first()\nExpected pattern: \u001b[32m/^The time is 2:40 AM on Thursday and the trading window is open$/\u001b[39m\nReceived string:  \u001b[31m\"The time is 1:40 AM on Thursday and the trading window is open\"\u001b[39m\nCall log:\n  \u001b[2m- Subheading should include correct time and day with timeout 1000ms\u001b[22m\n\u001b[2m  - waiting for locator('h4').first()\u001b[22m\n\u001b[2m  -   locator resolved to <h4>The time is 1:40 AM on Thursday and the trading w…</h4>\u001b[22m\n\u001b[2m  -   unexpected value \"The time is 1:40 AM on Thursday and the trading window is open\"\u001b[22m\n\u001b[2m  -   locator resolved to <h4>The time is 1:40 AM on Thursday and the trading w…</h4>\u001b[22m\n\u001b[2m  -   unexpected value \"The time is 1:40 AM on Thursday and the trading window is open\"\u001b[22m\n\u001b[2m  -   locator resolved to <h4>The time is 1:40 AM on Thursday and the trading w…</h4>\u001b[22m\n\u001b[2m  -   unexpected value \"The time is 1:40 AM on Thursday and the trading window is open\"\u001b[22m\n\u001b[2m  -   locator resolved to <h4>The time is 1:40 AM on Thursday and the trading w…</h4>\u001b[22m\n\u001b[2m  -   unexpected value \"The time is 1:40 AM on Thursday and the trading window is open\"\u001b[22m\n\u001b[2m  -   locator resolved to <h4>The time is 1:40 AM on Thursday and the trading w…</h4>\u001b[22m\n\u001b[2m  -   unexpected value \"The time is 1:40 AM on Thursday and the trading window is open\"\u001b[22m\n\n    at f:\\Code\\ENSEK-assignment\\ui-tests\\uiElements.spec.ts:126:8",
        "rawStatus": "failed",
        "tags": [],
        "type": "e2e",
        "filePath": "f:\\Code\\ENSEK-assignment\\ui-tests\\uiElements.spec.ts",
        "retries": 0,
        "flaky": false,
        "steps": [],
        "suite": "ui - Chrome > ui-tests\\uiElements.spec.ts > UI Elements",
        "extra": {
          "annotations": []
        }
      }
    ]
  }
}
